stdlib.py
flang.py
flang-0.1.1.dist-info/METADATA
flang-0.1.1.dist-info/RECORD
flang-0.1.1.dist-info/metadata.json
flang-0.1.1.dist-info/WHEEL
flang-0.1.1.dist-info/entry_points.txt
flang-0.1.1.dist-info/top_level.txt
flang-0.1.1.dist-info/DESCRIPTION.rst
