Metadata-Version: 2.0
Name: flang
Version: 0.1.1
Summary: A simple stack-based language for teaching programming concepts.
Home-page: https://gitlab.com/shakna-israel/flang
Author: James Milne
Author-email: james.milne@protonmail.com
License: MIT
Keywords: stack programming teach
Platform: UNKNOWN
Classifier: Development Status :: 3 - Alpha
Classifier: Intended Audience :: Education
Classifier: License :: OSI Approved :: MIT License
Classifier: Topic :: Education
Classifier: Programming Language :: Python :: 3
